xyz_mongo/__init__.py
xyz_mongo/config.py
xyz_mongo/filterset.py
xyz_mongo/lookup.py
xyz_mongo/query.py
xyz_mongo/reflect.py
xyz_mongo/rest_framework.py
xyz_mongo/schema.py
xyz_mongo/store.py
xyz_mongo/utils.py
xyz_mongo/reflects/__init__.py
xyz_mongo/reflects/djongo.py
xyz_mongo/reflects/mongoengine.py
xyz_mongo-0.0.3.dist-info/METADATA
xyz_mongo-0.0.3.dist-info/WHEEL
xyz_mongo-0.0.3.dist-info/top_level.txt
xyz_mongo-0.0.3.dist-info/RECORD
